codereader/__init__.py
codereader/cli.py
codereader/logger/result_logger.py
codereader/orchestration/grading_engine.py
codereader/orchestration/runner_manager.py
codereader/runners/llama_runner.py
codereader/runners/ollama_runner.py
codereader/runners/prompts.py
codereader/runners/runner.py
codereader/runners/transformers_runner.py
codereader-0.2.0.dist-info/entry_points.txt
codereader-0.2.0.dist-info/licenses/LICENSE
codereader-0.2.0.dist-info/METADATA
codereader-0.2.0.dist-info/WHEEL
codereader-0.2.0.dist-info/RECORD
