Metadata-Version: 2.4
Name: codereader
Version: 0.2.0
Summary: Local code readability grader using LLMs
License: GPLv3
License-File: LICENSE
Author: Jason Liu
Author-email: Liujason2003@gmail.com
Requires-Python: >=3.12
Classifier: License :: OSI Approved :: GNU General Public License v3 (GPLv3)
Classifier: Programming Language :: Python :: 3
Classifier: Programming Language :: Python :: 3.12
Classifier: Operating System :: OS Independent
Requires-Dist: anyio (>=4.12.1,<5.0.0)
Requires-Dist: orjson (>=3.11.5,<4.0.0)
Requires-Dist: pydantic (>=2.12.5,<3.0.0)
Requires-Dist: pyyaml (>=6.0.3,<7.0.0)
Requires-Dist: rich (>=14.2.0,<15.0.0)
Requires-Dist: typer (>=0.21.1,<0.22.0)
